distributions_pckg
