Metadata-Version: 1.0
Name: distributions-pckg
Version: 0.3
Summary: Gaussian distributions
Home-page: UNKNOWN
Author: Andrew Paster
Author-email: bour.walae@gmail.com
License: UNKNOWN
Platform: UNKNOWN
